Metadata-Version: 1.1
Name: vasil
Version: 0.0.2
Summary: A very basic pussy
Home-page: UNKNOWN
Author: Grigoriy Skovoroda
Author-email: SuckME@g.org
License: MIT
Keywords: vasil
Platform: UNKNOWN
Classifier: Development Status :: 5 - Production/Stable
Classifier: Intended Audience :: Education
Classifier: Operating System :: Microsoft :: Windows :: Windows 10
Classifier: License :: OSI Approved :: MIT License
Classifier: Programming Language :: Python :: 3
